libemail/__init__.py
libemail/apps.py
libemail/generic.py
libemail/templates/libemail/generic.html
libemail/templates/libemail/generic_uncompiled.html
libemail-0.1.0.dist-info/WHEEL
libemail-0.1.0.dist-info/METADATA
libemail-0.1.0.dist-info/RECORD
