Metadata-Version: 2.1
Name: libemail
Version: 0.1.0
Summary: Thin wrapper for Django EmailMessage
Author: Eglenelid Gamaliel Gutierrez Hernandez
Author-email: eglenelid.gamaliel@gmail.com
Requires-Python: >=3.8.0,<4.0.0
Classifier: Programming Language :: Python :: 3
Classifier: Programming Language :: Python :: 3.8
Classifier: Programming Language :: Python :: 3.9
Classifier: Programming Language :: Python :: 3.10
Classifier: Programming Language :: Python :: 3.11
Requires-Dist: django (>=3.0,<=5.0)
